jira_agile_metrics/__init__.py
jira_agile_metrics/calculator.py
jira_agile_metrics/calculator_test.py
jira_agile_metrics/cli.py
jira_agile_metrics/cli_test.py
jira_agile_metrics/config.py
jira_agile_metrics/config_test.py
jira_agile_metrics/conftest.py
jira_agile_metrics/querymanager.py
jira_agile_metrics/querymanager_test.py
jira_agile_metrics/utils.py
jira_agile_metrics/utils_test.py
jira_agile_metrics/calculators/__init__.py
jira_agile_metrics/calculators/ageingwip.py
jira_agile_metrics/calculators/ageingwip_test.py
jira_agile_metrics/calculators/burnup.py
jira_agile_metrics/calculators/burnup_test.py
jira_agile_metrics/calculators/cfd.py
jira_agile_metrics/calculators/cfd_test.py
jira_agile_metrics/calculators/cycletime.py
jira_agile_metrics/calculators/cycletime_test.py
jira_agile_metrics/calculators/debt.py
jira_agile_metrics/calculators/debt_test.py
jira_agile_metrics/calculators/defects.py
jira_agile_metrics/calculators/defects_test.py
jira_agile_metrics/calculators/forecast.py
jira_agile_metrics/calculators/forecast_test.py
jira_agile_metrics/calculators/histogram.py
jira_agile_metrics/calculators/histogram_test.py
jira_agile_metrics/calculators/impediments.py
jira_agile_metrics/calculators/impediments_test.py
jira_agile_metrics/calculators/netflow.py
jira_agile_metrics/calculators/netflow_test.py
jira_agile_metrics/calculators/percentiles.py
jira_agile_metrics/calculators/percentiles_test.py
jira_agile_metrics/calculators/progressreport.py
jira_agile_metrics/calculators/progressreport_template.html
jira_agile_metrics/calculators/progressreport_test.py
jira_agile_metrics/calculators/scatterplot.py
jira_agile_metrics/calculators/scatterplot_test.py
jira_agile_metrics/calculators/throughput.py
jira_agile_metrics/calculators/throughput_test.py
jira_agile_metrics/calculators/waste.py
jira_agile_metrics/calculators/waste_test.py
jira_agile_metrics/calculators/wip.py
jira_agile_metrics/calculators/wip_test.py
jira_agile_metrics-0.24.dist-info/METADATA
jira_agile_metrics-0.24.dist-info/RECORD
jira_agile_metrics-0.24.dist-info/WHEEL
jira_agile_metrics-0.24.dist-info/entry_points.txt
jira_agile_metrics-0.24.dist-info/top_level.txt
