Metadata-Version: 2.1
Name: jira-agile-metrics
Version: 0.24
Summary: Agile metrics and summary data extracted from JIRA
Home-page: https://github.com/optilude/jira-agile-metrics
Author: Martin Aspeli
Author-email: optilude@gmail.com
License: MIT
Keywords: agile jira analytics metrics
Platform: UNKNOWN
Requires-Dist: cryptography
Requires-Dist: pyjwt
Requires-Dist: requests-oauthlib (>=1.2.0)
Requires-Dist: jira
Requires-Dist: PyYAML
Requires-Dist: pandas (>=0.23.0)
Requires-Dist: numpy
Requires-Dist: seaborn
Requires-Dist: matplotlib
Requires-Dist: statsmodels
Requires-Dist: python-dateutil
Requires-Dist: pydicti
Requires-Dist: openpyxl
Requires-Dist: flask
Requires-Dist: Jinja2
